v8unpack/__init__.py
v8unpack/__main__.py
v8unpack/container.py
v8unpack/container_doc.py
v8unpack/container_reader.py
v8unpack/container_writer.py
v8unpack/decoder.py
v8unpack/ext_exception.py
v8unpack/helper.py
v8unpack/index.py
v8unpack/json_container_decoder.py
v8unpack/metadata_types.py
v8unpack/organizer_code.py
v8unpack/organizer_file.py
v8unpack/organizer_file_ce.py
v8unpack/organizer_form_elem.py
v8unpack/unittest_helper.py
v8unpack/v8unpack.py
v8unpack/version.py
v8unpack/MetaDataObject/AccountingRegister.py
v8unpack/MetaDataObject/AccountingRegisterCommand.py
v8unpack/MetaDataObject/AccountingRegisterForm.py
v8unpack/MetaDataObject/AccumulationRegister.py
v8unpack/MetaDataObject/AccumulationRegisterCommand.py
v8unpack/MetaDataObject/AccumulationRegisterForm.py
v8unpack/MetaDataObject/Bot.py
v8unpack/MetaDataObject/BusinessProcess.py
v8unpack/MetaDataObject/BusinessProcessCommand.py
v8unpack/MetaDataObject/BusinessProcessForm.py
v8unpack/MetaDataObject/CalculationRegister.py
v8unpack/MetaDataObject/CalculationRegisterCommand.py
v8unpack/MetaDataObject/CalculationRegisterForm.py
v8unpack/MetaDataObject/CalculationRegisterRecalculations.py
v8unpack/MetaDataObject/Catalog.py
v8unpack/MetaDataObject/CatalogCommand.py
v8unpack/MetaDataObject/CatalogForm.py
v8unpack/MetaDataObject/ChartOfAccounts.py
v8unpack/MetaDataObject/ChartOfAccountsCommand.py
v8unpack/MetaDataObject/ChartOfAccountsForm.py
v8unpack/MetaDataObject/ChartOfCalculationTypes.py
v8unpack/MetaDataObject/ChartOfCalculationTypesCommand.py
v8unpack/MetaDataObject/ChartOfCalculationTypesForm.py
v8unpack/MetaDataObject/ChartOfCharacteristicType.py
v8unpack/MetaDataObject/ChartOfCharacteristicTypeCommand.py
v8unpack/MetaDataObject/ChartOfCharacteristicTypeForm.py
v8unpack/MetaDataObject/CommandGroup.py
v8unpack/MetaDataObject/CommonAttribute.py
v8unpack/MetaDataObject/CommonCommand.py
v8unpack/MetaDataObject/CommonForm.py
v8unpack/MetaDataObject/CommonModule.py
v8unpack/MetaDataObject/CommonPicture.py
v8unpack-1.2.6.dist-info/licenses/LICENSE
v8unpack-1.2.6.dist-info/METADATA
v8unpack-1.2.6.dist-info/WHEEL
v8unpack-1.2.6.dist-info/entry_points.txt
v8unpack-1.2.6.dist-info/top_level.txt
v8unpack-1.2.6.dist-info/RECORD
