Metadata-Version: 2.4
Name: v8unpack
Version: 1.2.6
Summary: Unpacking binaries 1C to JSON for GIT
Author-email: Razgovorov Mikhail <1338833@gmail.com>
License-Expression: MIT
Project-URL: Homepage, https://github.com/saby-integration/v8unpack
Project-URL: Issues, https://github.com/saby-integration/v8unpack/issues
Keywords: 1c,cf,cfe,epf,v8unpack,saby,sbis,сбис,1с
Classifier: Development Status :: 5 - Production/Stable
Classifier: Natural Language :: Russian
Classifier: Programming Language :: Python :: 3
Classifier: Topic :: Software Development
Classifier: Operating System :: OS Independent
Requires-Python: >=3.7
License-File: LICENSE
Requires-Dist: tqdm>=4
Dynamic: license-file
